trusty/__init__.py
trusty/trusty.py
trusty-1.1.0.dist-info/METADATA
trusty-1.1.0.dist-info/WHEEL
trusty-1.1.0.dist-info/top_level.txt
trusty-1.1.0.dist-info/RECORD
