Metadata-Version: 2.1
Name: trusty
Version: 1.1.0
Summary: Persistent dictionaries
Home-page: 
Author: Chris Varga
Author-email: 
Keywords: trusty dictionary json persistent
Classifier: Programming Language :: Python
Classifier: License :: OSI Approved :: MIT License
Classifier: Operating System :: OS Independent
